{
  "variants": {
    "waterlogged=false,east=false,north=false,south=false,west=false,up=true": { "model": "block/unused_cross_0" },
    "waterlogged=false,east=false,north=false,south=false,west=false,up=false": { "model": "block/unused_cross_0" },
    "waterlogged=false,east=false,north=false,south=false,west=true,up=true": { "model": "block/unused_cross_0" },
    "waterlogged=false,east=false,north=false,south=false,west=true,up=false": { "model": "block/unused_cross_0" },
    "waterlogged=false,east=false,north=false,south=true,west=false,up=true": { "model": "block/unused_cross_0" },
    "waterlogged=false,east=false,north=false,south=true,west=false,up=false": { "model": "block/unused_cross_0" },
    "waterlogged=false,east=false,north=false,south=true,west=true,up=true": { "model": "block/unused_cross_0" },
    "waterlogged=false,east=false,north=false,south=true,west=true,up=false": { "model": "block/unused_cross_0" },
    "waterlogged=false,east=false,north=true,south=false,west=false,up=true": { "model": "block/unused_cross_0" },
    "waterlogged=false,east=false,north=true,south=false,west=false,up=false": { "model": "block/unused_cross_0" },
    "waterlogged=false,east=false,north=true,south=false,west=true,up=true": { "model": "block/unused_cross_0" },
    "waterlogged=false,east=false,north=true,south=false,west=true,up=false": { "model": "block/unused_cross_0" },
    "waterlogged=false,east=false,north=true,south=true,west=false,up=true": { "model": "block/unused_cross_0" },
    "waterlogged=false,east=false,north=true,south=true,west=false,up=false": { "model": "block/unused_cross_0" },
    "waterlogged=false,east=false,north=true,south=true,west=true,up=true": { "model": "block/unused_cross_0" },
    "waterlogged=false,east=false,north=true,south=true,west=true,up=false": { "model": "block/unused_cross_0" },
    "waterlogged=false,east=true,north=false,south=false,west=false,up=true": { "model": "block/unused_cross_0" },
    "waterlogged=false,east=true,north=false,south=false,west=false,up=false": { "model": "block/unused_cross_0" },
    "waterlogged=false,east=true,north=false,south=false,west=true,up=true": { "model": "block/unused_cross_0" },
    "waterlogged=false,east=true,north=false,south=false,west=true,up=false": { "model": "block/unused_cross_0" },
    "waterlogged=false,east=true,north=false,south=true,west=false,up=true": { "model": "block/unused_cross_0" },
    "waterlogged=false,east=true,north=false,south=true,west=false,up=false": { "model": "block/unused_cross_0" },
    "waterlogged=false,east=true,north=false,south=true,west=true,up=true": { "model": "block/unused_cross_0" },
    "waterlogged=false,east=true,north=false,south=true,west=true,up=false": { "model": "block/unused_cross_0" },
    "waterlogged=false,east=true,north=true,south=false,west=false,up=true": { "model": "block/unused_cross_0" },
    "waterlogged=false,east=true,north=true,south=false,west=false,up=false": { "model": "block/unused_cross_0" },
    "waterlogged=false,east=true,north=true,south=false,west=true,up=true":  { "model": "block/unused_cross_0" },
    "waterlogged=false,east=true,north=true,south=false,west=true,up=false": { "model": "block/unused_cross_0" },
    "waterlogged=false,east=true,north=true,south=true,west=false,up=true": { "model": "block/unused_cross_0" },
    "waterlogged=false,east=true,north=true,south=true,west=false,up=false": { "model": "block/unused_cross_0" },
    "waterlogged=false,east=true,north=true,south=true,west=true,up=true": { "model": "block/unused_cross_0"},
    "waterlogged=false,east=true,north=true,south=true,west=true,up=false": { "model": "block/unused_cross_0" },
    "waterlogged=true,east=false,north=false,south=false,west=false,up=true": { "model": "block/unused_cross_0" },
    "waterlogged=true,east=false,north=false,south=false,west=false,up=false": { "model": "block/unused_cross_0" },
    "waterlogged=true,east=false,north=false,south=false,west=true,up=true": { "model": "block/unused_cross_0" },
    "waterlogged=true,east=false,north=false,south=false,west=true,up=false": { "model": "block/unused_cross_0" },
    "waterlogged=true,east=false,north=false,south=true,west=false,up=true": { "model": "block/unused_cross_0" },
    "waterlogged=true,east=false,north=false,south=true,west=false,up=false": { "model": "block/unused_cross_0" },
    "waterlogged=true,east=false,north=false,south=true,west=true,up=true": { "model": "block/unused_cross_0" },
    "waterlogged=true,east=false,north=false,south=true,west=true,up=false": { "model": "block/unused_cross_0" },
    "waterlogged=true,east=false,north=true,south=false,west=false,up=true": { "model": "block/unused_cross_0" },
    "waterlogged=true,east=false,north=true,south=false,west=false,up=false": { "model": "block/unused_cross_0" },
    "waterlogged=true,east=false,north=true,south=false,west=true,up=true": { "model": "block/unused_cross_0" },
    "waterlogged=true,east=false,north=true,south=false,west=true,up=false": { "model": "block/unused_cross_0" },
    "waterlogged=true,east=false,north=true,south=true,west=false,up=true": { "model": "block/unused_cross_0" },
    "waterlogged=true,east=false,north=true,south=true,west=false,up=false": { "model": "block/unused_cross_0" },
    "waterlogged=true,east=false,north=true,south=true,west=true,up=true": { "model": "block/unused_cross_0" },
    "waterlogged=true,east=false,north=true,south=true,west=true,up=false": { "model": "block/unused_cross_0" },
    "waterlogged=true,east=true,north=false,south=false,west=false,up=true": { "model": "block/unused_cross_0" },
    "waterlogged=true,east=true,north=false,south=false,west=false,up=false": { "model": "block/unused_cross_0" },
    "waterlogged=true,east=true,north=false,south=false,west=true,up=true": { "model": "block/unused_cross_0" },
    "waterlogged=true,east=true,north=false,south=false,west=true,up=false": { "model": "block/unused_cross_0" },
    "waterlogged=true,east=true,north=false,south=true,west=false,up=true": { "model": "block/unused_cross_0" },
    "waterlogged=true,east=true,north=false,south=true,west=false,up=false": { "model": "block/unused_cross_0" },
    "waterlogged=true,east=true,north=false,south=true,west=true,up=true": { "model": "block/unused_cross_0" },
    "waterlogged=true,east=true,north=false,south=true,west=true,up=false": { "model": "block/unused_cross_0" },
    "waterlogged=true,east=true,north=true,south=false,west=false,up=true": { "model": "block/unused_cross_0" },
    "waterlogged=true,east=true,north=true,south=false,west=false,up=false": { "model": "block/unused_cross_0" },
    "waterlogged=true,east=true,north=true,south=false,west=true,up=true":  { "model": "block/unused_cross_0" },
    "waterlogged=true,east=true,north=true,south=false,west=true,up=false": { "model": "block/unused_cross_0" },
    "waterlogged=true,east=true,north=true,south=true,west=false,up=true": { "model": "block/unused_cross_0" },
    "waterlogged=true,east=true,north=true,south=true,west=false,up=false": { "model": "block/unused_cross_0" },
    "waterlogged=true,east=true,north=true,south=true,west=true,up=true": { "model": "block/unused_cross_0" },
    "waterlogged=true,east=true,north=true,south=true,west=true,up=false": { "model": "block/unused_cross_0" }
  }
}
